ScratchLatch.py
ScratchLatch-1.1.dist-info/METADATA
ScratchLatch-1.1.dist-info/WHEEL
ScratchLatch-1.1.dist-info/top_level.txt
ScratchLatch-1.1.dist-info/RECORD
