Metadata-Version: 2.1
Name: ScratchLatch
Version: 1.1
Summary: Scratch's most simple Python Library!
Home-page: https://github.com/kruffer/ScratchLatch
Author: Kruffer
Author-email: kruffer99@gmail.com
License: UNKNOWN
Platform: UNKNOWN
Classifier: Intended Audience :: Developers
Classifier: License :: OSI Approved :: MIT License
Classifier: Programming Language :: Python :: 3
Classifier: Topic :: Utilities
Requires-Python: >=3.6
Requires-Dist: websocket
